libcgroup_bind/__init__.py
libcgroup_bind/__init__.pyi
libcgroup_bind/config.py
libcgroup_bind/config.pyi
libcgroup_bind/error.py
libcgroup_bind/error.pyi
libcgroup_bind/groups.py
libcgroup_bind/groups.pyi
libcgroup_bind/init.py
libcgroup_bind/init.pyi
libcgroup_bind/iterators.py
libcgroup_bind/iterators.pyi
libcgroup_bind/log.py
libcgroup_bind/log.pyi
libcgroup_bind/tasks.py
libcgroup_bind/tasks.pyi
libcgroup_bind-1.0.7.dist-info/COPYING
libcgroup_bind-1.0.7.dist-info/COPYING.LESSER
libcgroup_bind-1.0.7.dist-info/METADATA
libcgroup_bind-1.0.7.dist-info/WHEEL
libcgroup_bind-1.0.7.dist-info/top_level.txt
libcgroup_bind-1.0.7.dist-info/RECORD
